articleparse/__init__.py
articleparse/analyzer.py
articleparse/htmlparse.py
articleparse/stopwords.py
articleparse-0.2.1.dist-info/DESCRIPTION.rst
articleparse-0.2.1.dist-info/METADATA
articleparse-0.2.1.dist-info/RECORD
articleparse-0.2.1.dist-info/WHEEL
articleparse-0.2.1.dist-info/metadata.json
articleparse-0.2.1.dist-info/top_level.txt
