Metadata-Version: 2.0
Name: articleparse
Version: 0.2.1
Summary: Heuristic text extraction from news articles
Home-page: https://github.com/bmoscon/articleparse
Author: Bryant Moscon
Author-email: bmoscon@gmail.com
License: XFree86
Keywords: text extraction
Platform: UNKNOWN
Classifier: Development Status :: 4 - Beta
Classifier: Programming Language :: Python :: 3.4
Classifier: Programming Language :: Python :: 3.5
Classifier: Programming Language :: Python :: 3.6
Classifier: Topic :: Software Development :: Libraries
